{
  "duration": 89.62000274658203,
  "language": "korean",
  "text": "제가 생각해도 마찬가지이긴 하지만 다른 주변 사람들이 저에게 말해준 단점은 추진력이 부족하다는 것입니다. 저는 어떤 것을 하는 데 있어서 계획을 잘 세웁니다. 하고 싶고 해야 하고 이런 것들은 계획을 세우고 해야겠다 마음은 먹지만, 막상 실천하는 것은 좀 드문 것 같습니다. 반드시 해야 할 경우 어떻게 나중에 실천을 하기는 하지만 계속 미루고 해야 하는데, 해야 하는데 이렇게 생각만 하는 경우가 자주 있는 것 같습니다. 그렇기 때문에 다른 사람들이 생각할 때 저는 계속 생각과 말만 하고 하지는 않는다고 그렇게 추진력은 부족한 것 같다고 이야기를 들었습니다. 그리고 다른 사람이 얘기해준 저의 장점은 공감 능력이라는 것입니다. 어떤 고민이나 이야기들을 저에게 이야기를 하면 항상 눈을 마주치며 이야기를 잘 들어주고 공감을 잘 해줘서 마음이 편하고 위로가 된다는 이야기를 많이 들었습니다.",
  "segments": [
    {
      "id": 0,
      "avg_logprob": -0.26434090733528137,
      "compression_ratio": 1.2674418687820435,
      "end": 12.640000343322754,
      "no_speech_prob": 0.2989111840724945,
      "seek": 0,
      "start": 0.0,
      "temperature": 0.0,
      "text": " 제가 생각해도 마찬가지이긴 하지만 다른 주변 사람들이 저에게 말해준 단점은 추진력이 부족하다는 것입니다.",
      "tokens": [
        50364,
        7439,
        8594,
        49183,
        6437,
        29434,
        26683,
        1129,
        17381,
        23286,
        16435,
        16410,
        43858,
        34919,
        4841,
        15989,
        7058,
        44487,
        222,
        16818,
        15046,
        2124,
        17435,
        1372,
        2703,
        11770,
        1129,
        11351,
        21799,
        2240,
        10520,
        4431,
        7416,
        13,
        51014
      ]
    },
    {
      "id": 1,
      "avg_logprob": -0.26434090733528137,
      "compression_ratio": 1.2674418687820435,
      "end": 19.559999465942383,
      "no_speech_prob": 0.2989111840724945,
      "seek": 0,
      "start": 13.399999618530273,
      "temperature": 0.0,
      "text": " 저는 어떤 것을 하는 데 있어서 계획을 잘 세웁니다.",
      "tokens": [
        51014,
        10551,
        15620,
        32746,
        10914,
        20883,
        27937,
        10603,
        40996,
        1638,
        6644,
        11605,
        3860,
        223,
        1972,
        13,
        51364
      ]
    },
    {
      "id": 2,
      "avg_logprob": -0.25892096757888794,
      "compression_ratio": 1.5758928060531616,
      "end": 27.639999389648438,
      "no_speech_prob": 0.36603859066963196,
      "seek": 1956,
      "start": 19.559999465942383,
      "temperature": 0.0,
      "text": " 하고 싶고 해야 하고 이런 것들은 계획을 세우고 해야겠다 마음은 먹지만,",
      "tokens": [
        50364,
        10301,
        10785,
        1313,
        20556,
        10301,
        8381,
        4431,
        14271,
        2124,
        10603,
        40996,
        1638,
        11605,
        7812,
        1313,
        20556,
        19715,
        20477,
        2124,
        6554,
        9231,
        11,
        50764
      ]
    },
    {
      "id": 3,
      "avg_logprob": -0.25892096757888794,
      "compression_ratio": 1.5758928060531616,
      "end": 31.399999618530273,
      "no_speech_prob": 0.36603859066963196,
      "seek": 1956,
      "start": 27.979999542236328,
      "temperature": 0.0,
      "text": " 막상 실천하는 것은 좀 드문 것 같습니다.",
      "tokens": [
        50764,
        14438,
        5979,
        19300,
        18906,
        7116,
        33825,
        6796,
        13356,
        8357,
        4431,
        31297,
        13,
        50964
      ]
    },
    {
      "id": 4,
      "avg_logprob": -0.25892096757888794,
      "compression_ratio": 1.5758928060531616,
      "end": 39.68000030517578,
      "no_speech_prob": 0.36603859066963196,
      "seek": 1956,
      "start": 32.459999084472656,
      "temperature": 0.0,
      "text": " 반드시 해야 할 경우 어떻게 나중에 실천을 하기는 하지만 계속 미루고",
      "tokens": [
        50964,
        23142,
        7087,
        3833,
        20556,
        8981,
        20591,
        12952,
        44865,
        19300,
        18906,
        1638,
        3369,
        23375,
        23286,
        17551,
        29004,
        13033,
        1313,
        51364
      ]
    },
    {
      "id": 5,
      "avg_logprob": -0.25892096757888794,
      "compression_ratio": 1.5758928060531616,
      "end": 45.08000183105469,
      "no_speech_prob": 0.36603859066963196,
      "seek": 1956,
      "start": 39.68000030517578,
      "temperature": 0.0,
      "text": " 해야 하는데, 해야 하는데 이렇게 생각만 하는 경우가 자주 있는 것 같습니다.",
      "tokens": [
        51364,
        20556,
        29600,
        11,
        20556,
        29600,
        5483,
        8594,
        5978,
        10914,
        20591,
        1453,
        47295,
        7153,
        4431,
        31297,
        13,
        51664
      ]
    },
    {
      "id": 6,
      "avg_logprob": -0.22629155218601227,
      "compression_ratio": 1.3902438879013062,
      "end": 54.79999923706055,
      "no_speech_prob": 0.21981565654277802,
      "seek": 4508,
      "start": 45.08000183105469,
      "temperature": 0.0,
      "text": " 그렇기 때문에 다른 사람들이 생각할 때 저는 계속 생각과 말만 하고",
      "tokens": [
        50364,
        13773,
        2401,
        12365,
        16435,
        34919,
        8594,
        7999,
        7765,
        10551,
        17551,
        8594,
        7097,
        1747,
        25940,
        10301,
        50864
      ]
    },
    {
      "id": 7,
      "avg_logprob": -0.22629155218601227,
      "compression_ratio": 1.3902438879013062,
      "end": 60.7400016784668,
      "no_speech_prob": 0.21981565654277802,
      "seek": 4508,
      "start": 54.79999923706055,
      "temperature": 0.0,
      "text": " 하지는 않는다고 그렇게 추진력은 부족한 것 같다고 이야기를 들었습니다.",
      "tokens": [
        50864,
        3369,
        20508,
        34790,
        7726,
        16104,
        17435,
        1372,
        2703,
        11770,
        2124,
        11351,
        21799,
        3049,
        4431,
        4385,
        7726,
        48974,
        6275,
        24148,
        13,
        51164
      ]
    },
    {
      "id": 8,
      "avg_logprob": -0.22629155218601227,
      "compression_ratio": 1.3902438879013062,
      "end": 69.12000274658203,
      "no_speech_prob": 0.21981565654277802,
      "seek": 4508,
      "start": 61.880001068115234,
      "temperature": 0.0,
      "text": " 그리고 다른 사람이 얘기해준 저의 장점은 공감 능력이라는 것입니다.",
      "tokens": [
        51164,
        8785,
        16435,
        27660,
        19641,
        44487,
        222,
        4841,
        2785,
        12280,
        15046,
        2124,
        9273,
        13664,
        7707,
        98,
        21946,
        32103,
        4431,
        7416,
        13,
        51564
      ]
    },
    {
      "id": 9,
      "avg_logprob": -0.18510998785495758,
      "compression_ratio": 1.3937499523162842,
      "end": 79.12000274658203,
      "no_speech_prob": 0.3624175190925598,
      "seek": 6912,
      "start": 69.12000274658203,
      "temperature": 0.0,
      "text": " 어떤 고민이나 이야기들을 저에게 이야기를 하면 항상 눈을 마주치며",
      "tokens": [
        50364,
        15620,
        41936,
        21672,
        20510,
        7091,
        24968,
        4841,
        15989,
        48974,
        17422,
        30747,
        15333,
        1638,
        6437,
        5836,
        31678,
        18095,
        50864
      ]
    },
    {
      "id": 10,
      "avg_logprob": -0.18510998785495758,
      "compression_ratio": 1.3937499523162842,
      "end": 88.5999984741211,
      "no_speech_prob": 0.3624175190925598,
      "seek": 6912,
      "start": 79.66000366210938,
      "temperature": 0.0,
      "text": " 이야기를 잘 들어주고 공감을 잘 해줘서 마음이 편하고 위로가 된다는 이야기를 많이 들었습니다.",
      "tokens": [
        50864,
        48974,
        6644,
        20744,
        11372,
        1313,
        9273,
        47004,
        6644,
        29409,
        246,
        2393,
        20477,
        1129,
        16990,
        7040,
        4916,
        14046,
        1453,
        16975,
        10520,
        48974,
        8358,
        6275,
        24148,
        13,
        51364
      ]
    }
  ],
  "words": [
    {
      "end": 1.6799999475479126,
      "start": 0.0,
      "word": "제가"
    },
    {
      "end": 2.640000104904175,
      "start": 1.6799999475479126,
      "word": "생각해도"
    },
    {
      "end": 3.9800000190734863,
      "start": 2.640000104904175,
      "word": "마찬가지이긴"
    },
    {
      "end": 4.380000114440918,
      "start": 3.9800000190734863,
      "word": "하지만"
    },
    {
      "end": 5.400000095367432,
      "start": 4.380000114440918,
      "word": "다른"
    },
    {
      "end": 5.820000171661377,
      "start": 5.400000095367432,
      "word": "주변"
    },
    {
      "end": 6.519999980926514,
      "start": 5.820000171661377,
      "word": "사람들이"
    },
    {
      "end": 7.71999979019165,
      "start": 6.519999980926514,
      "word": "저에게"
    },
    {
      "end": 8.420000076293945,
      "start": 7.71999979019165,
      "word": "말해준"
    },
    {
      "end": 10.279999732971191,
      "start": 8.420000076293945,
      "word": "단점은"
    },
    {
      "end": 11.199999809265137,
      "start": 10.279999732971191,
      "word": "추진력이"
    },
    {
      "end": 11.819999694824219,
      "start": 11.199999809265137,
      "word": "부족하다는"
    },
    {
      "end": 12.640000343322754,
      "start": 11.819999694824219,
      "word": "것입니다"
    },
    {
      "end": 14.0600004196167,
      "start": 13.399999618530273,
      "word": "저는"
    },
    {
      "end": 15.319999694824219,
      "start": 14.0600004196167,
      "word": "어떤"
    },
    {
      "end": 15.84000015258789,
      "start": 15.319999694824219,
      "word": "것을"
    },
    {
      "end": 16.299999237060547,
      "start": 15.84000015258789,
      "word": "하는"
    },
    {
      "end": 16.479999542236328,
      "start": 16.299999237060547,
      "word": "데"
    },
    {
      "end": 17.299999237060547,
      "start": 16.479999542236328,
      "word": "있어서"
    },
    {
      "end": 18.219999313354492,
      "start": 17.299999237060547,
      "word": "계획을"
    },
    {
      "end": 18.600000381469727,
      "start": 18.219999313354492,
      "word": "잘"
    },
    {
      "end": 19.559999465942383,
      "start": 18.600000381469727,
      "word": "세웁니다"
    },
    {
      "end": 20.200000762939453,
      "start": 19.559999465942383,
      "word": "하고"
    },
    {
      "end": 21.0,
      "start": 20.200000762939453,
      "word": "싶고"
    },
    {
      "end": 21.559999465942383,
      "start": 21.0,
      "word": "해야"
    },
    {
      "end": 22.139999389648438,
      "start": 21.559999465942383,
      "word": "하고"
    },
    {
      "end": 22.799999237060547,
      "start": 22.139999389648438,
      "word": "이런"
    },
    {
      "end": 23.860000610351562,
      "start": 22.799999237060547,
      "word": "것들은"
    },
    {
      "end": 24.520000457763672,
      "start": 23.860000610351562,
      "word": "계획을"
    },
    {
      "end": 25.440000534057617,
      "start": 24.520000457763672,
      "word": "세우고"
    },
    {
      "end": 26.020000457763672,
      "start": 25.440000534057617,
      "word": "해야겠다"
    },
    {
      "end": 26.700000762939453,
      "start": 26.020000457763672,
      "word": "마음은"
    },
    {
      "end": 27.639999389648438,
      "start": 26.700000762939453,
      "word": "먹지만"
    },
    {
      "end": 28.440000534057617,
      "start": 27.979999542236328,
      "word": "막상"
    },
    {
      "end": 29.399999618530273,
      "start": 28.440000534057617,
      "word": "실천하는"
    },
    {
      "end": 29.780000686645508,
      "start": 29.399999618530273,
      "word": "것은"
    },
    {
      "end": 30.31999969482422,
      "start": 29.780000686645508,
      "word": "좀"
    },
    {
      "end": 30.440000534057617,
      "start": 30.31999969482422,
      "word": "드문"
    },
    {
      "end": 30.639999389648438,
      "start": 30.440000534057617,
      "word": "것"
    },
    {
      "end": 31.399999618530273,
      "start": 30.639999389648438,
      "word": "같습니다"
    },
    {
      "end": 32.779998779296875,
      "start": 32.459999084472656,
      "word": "반드시"
    },
    {
      "end": 33.15999984741211,
      "start": 32.779998779296875,
      "word": "해야"
    },
    {
      "end": 33.400001525878906,
      "start": 33.15999984741211,
      "word": "할"
    },
    {
      "end": 34.15999984741211,
      "start": 33.400001525878906,
      "word": "경우"
    },
    {
      "end": 35.41999816894531,
      "start": 34.15999984741211,
      "word": "어떻게"
    },
    {
      "end": 36.08000183105469,
      "start": 35.41999816894531,
      "word": "나중에"
    },
    {
      "end": 36.70000076293945,
      "start": 36.08000183105469,
      "word": "실천을"
    },
    {
      "end": 37.13999938964844,
      "start": 36.70000076293945,
      "word": "하기는"
    },
    {
      "end": 37.939998626708984,
      "start": 37.13999938964844,
      "word": "하지만"
    },
    {
      "end": 38.7400016784668,
      "start": 37.939998626708984,
      "word": "계속"
    },
    {
      "end": 39.68000030517578,
      "start": 38.7400016784668,
      "word": "미루고"
    },
    {
      "end": 39.959999084472656,
      "start": 39.68000030517578,
      "word": "해야"
    },
    {
      "end": 40.5,
      "start": 39.959999084472656,
      "word": "하는데"
    },
    {
      "end": 41.040000915527344,
      "start": 40.900001525878906,
      "word": "해야"
    },
    {
      "end": 41.47999954223633,
      "start": 41.040000915527344,
      "word": "하는데"
    },
    {
      "end": 41.97999954223633,
      "start": 41.47999954223633,
      "word": "이렇게"
    },
    {
      "end": 42.68000030517578,
      "start": 41.97999954223633,
      "word": "생각만"
    },
    {
      "end": 42.959999084472656,
      "start": 42.68000030517578,
      "word": "하는"
    },
    {
      "end": 43.84000015258789,
      "start": 42.959999084472656,
      "word": "경우가"
    },
    {
      "end": 44.20000076293945,
      "start": 43.84000015258789,
      "word": "자주"
    },
    {
      "end": 44.41999816894531,
      "start": 44.20000076293945,
      "word": "있는"
    },
    {
      "end": 44.720001220703125,
      "start": 44.41999816894531,
      "word": "것"
    },
    {
      "end": 45.08000183105469,
      "start": 44.720001220703125,
      "word": "같습니다"
    },
    {
      "end": 47.13999938964844,
      "start": 45.08000183105469,
      "word": "그렇기"
    },
    {
      "end": 47.779998779296875,
      "start": 47.13999938964844,
      "word": "때문에"
    },
    {
      "end": 49.29999923706055,
      "start": 47.779998779296875,
      "word": "다른"
    },
    {
      "end": 50.13999938964844,
      "start": 49.29999923706055,
      "word": "사람들이"
    },
    {
      "end": 50.79999923706055,
      "start": 50.13999938964844,
      "word": "생각할"
    },
    {
      "end": 51.15999984741211,
      "start": 50.79999923706055,
      "word": "때"
    },
    {
      "end": 51.880001068115234,
      "start": 51.15999984741211,
      "word": "저는"
    },
    {
      "end": 52.7400016784668,
      "start": 51.880001068115234,
      "word": "계속"
    },
    {
      "end": 53.29999923706055,
      "start": 52.7400016784668,
      "word": "생각과"
    },
    {
      "end": 53.7400016784668,
      "start": 53.29999923706055,
      "word": "말만"
    },
    {
      "end": 54.79999923706055,
      "start": 53.7400016784668,
      "word": "하고"
    },
    {
      "end": 55.900001525878906,
      "start": 54.79999923706055,
      "word": "하지는"
    },
    {
      "end": 56.84000015258789,
      "start": 55.900001525878906,
      "word": "않는다고"
    },
    {
      "end": 57.29999923706055,
      "start": 56.84000015258789,
      "word": "그렇게"
    },
    {
      "end": 58.040000915527344,
      "start": 57.29999923706055,
      "word": "추진력은"
    },
    {
      "end": 58.65999984741211,
      "start": 58.040000915527344,
      "word": "부족한"
    },
    {
      "end": 58.84000015258789,
      "start": 58.65999984741211,
      "word": "것"
    },
    {
      "end": 59.36000061035156,
      "start": 58.84000015258789,
      "word": "같다고"
    },
    {
      "end": 59.91999816894531,
      "start": 59.36000061035156,
      "word": "이야기를"
    },
    {
      "end": 60.7400016784668,
      "start": 59.91999816894531,
      "word": "들었습니다"
    },
    {
      "end": 62.34000015258789,
      "start": 61.880001068115234,
      "word": "그리고"
    },
    {
      "end": 62.86000061035156,
      "start": 62.34000015258789,
      "word": "다른"
    },
    {
      "end": 63.279998779296875,
      "start": 62.86000061035156,
      "word": "사람이"
    },
    {
      "end": 63.939998626708984,
      "start": 63.279998779296875,
      "word": "얘기해준"
    },
    {
      "end": 64.36000061035156,
      "start": 63.939998626708984,
      "word": "저의"
    },
    {
      "end": 66.69999694824219,
      "start": 64.36000061035156,
      "word": "장점은"
    },
    {
      "end": 67.58000183105469,
      "start": 66.69999694824219,
      "word": "공감"
    },
    {
      "end": 68.41999816894531,
      "start": 67.58000183105469,
      "word": "능력이라는"
    },
    {
      "end": 69.12000274658203,
      "start": 68.41999816894531,
      "word": "것입니다"
    },
    {
      "end": 70.86000061035156,
      "start": 69.12000274658203,
      "word": "어떤"
    },
    {
      "end": 72.81999969482422,
      "start": 70.86000061035156,
      "word": "고민이나"
    },
    {
      "end": 74.26000213623047,
      "start": 72.81999969482422,
      "word": "이야기들을"
    },
    {
      "end": 74.9000015258789,
      "start": 74.26000213623047,
      "word": "저에게"
    },
    {
      "end": 75.73999786376953,
      "start": 74.9000015258789,
      "word": "이야기를"
    },
    {
      "end": 76.23999786376953,
      "start": 75.73999786376953,
      "word": "하면"
    },
    {
      "end": 77.18000030517578,
      "start": 76.23999786376953,
      "word": "항상"
    },
    {
      "end": 78.33999633789062,
      "start": 77.18000030517578,
      "word": "눈을"
    },
    {
      "end": 79.12000274658203,
      "start": 78.33999633789062,
      "word": "마주치며"
    },
    {
      "end": 80.26000213623047,
      "start": 79.66000366210938,
      "word": "이야기를"
    },
    {
      "end": 80.69999694824219,
      "start": 80.26000213623047,
      "word": "잘"
    },
    {
      "end": 81.83999633789062,
      "start": 80.69999694824219,
      "word": "들어주고"
    },
    {
      "end": 82.37999725341797,
      "start": 81.83999633789062,
      "word": "공감을"
    },
    {
      "end": 82.95999908447266,
      "start": 82.37999725341797,
      "word": "잘"
    },
    {
      "end": 84.22000122070312,
      "start": 82.95999908447266,
      "word": "해줘서"
    },
    {
      "end": 84.76000213623047,
      "start": 84.22000122070312,
      "word": "마음이"
    },
    {
      "end": 85.68000030517578,
      "start": 84.76000213623047,
      "word": "편하고"
    },
    {
      "end": 86.33999633789062,
      "start": 85.68000030517578,
      "word": "위로가"
    },
    {
      "end": 86.76000213623047,
      "start": 86.33999633789062,
      "word": "된다는"
    },
    {
      "end": 87.33999633789062,
      "start": 86.76000213623047,
      "word": "이야기를"
    },
    {
      "end": 87.95999908447266,
      "start": 87.33999633789062,
      "word": "많이"
    },
    {
      "end": 88.5999984741211,
      "start": 87.95999908447266,
      "word": "들었습니다"
    }
  ],
  "task": "transcribe",
  "usage": {
    "type": "duration",
    "seconds": 90
  }
}